{"data":{"code":"0","message":"请求成功","appChosenProductInfoTitle":{"resourceId":"20181002","title":"小铂精选","subTitle":"走心推荐，实用好物","imageUrl":null,"skpUrl":null},"appChosenProductInfo":{"resourceId":"20181003","title":"茶人岭柠檬红茶小青柠茶臻享礼盒 160g","subTitle":null,"imageUrl":"https://imagemall.plateno.com/images/inn/18Pu6gNABt","skpUrl":"https://malls.bestwehotel.com/?sid=418000#/goodsDetail?productId=5952"},"appPointPromotionProductInfoTitle":{"resourceId":"20181004","title":"积分兑换","subTitle":"积分加钱购，好物够实惠","imageUrl":null,"skpUrl":"https://malls.bestwehotel.com/?sid=418001#/redeem"},"appPointPromotionProductInfo":{"resourceId":"20181005","title":"旅行功夫茶具（1壶2杯）","subTitle":"剩余316件","imageUrl":"https://imagemall.plateno.com/images/inn/16DYZI7Wok","skpUrl":"https://malls.bestwehotel.com/?sid=418001#/goodsDetail?productId=198&pointActivityId=16","favorPoints":"919积分","favorPrice":"￥54"},"appRecommendNewProductInfoTitle":{"resourceId":"20181006","title":"新品首发","subTitle":"新品抢先试，上新有惊喜","imageUrl":null,"skpUrl":"https://malls.bestwehotel.com/?sid=418002#/goodsIndex"},"appRecommendNewProductInfoList":[{"resourceId":"20181007","title":"￥282","subTitle":null,"imageUrl":"https://imagemall.plateno.com/images/inn/18NVOfzsyG","skpUrl":"https://malls.bestwehotel.com/?sid=418002#/goodsDetail?productId=5909","point":"4693积分"},{"resourceId":"20181008","title":"￥20","subTitle":null,"imageUrl":"https://imagemall.plateno.com/images/inn/18STQ0Jxv3","skpUrl":"https://malls.bestwehotel.com/?sid=418002#/goodsDetail?productId=6109","point":"332积分"},{"resourceId":"20181009","title":"￥9","subTitle":null,"imageUrl":"https://imagemall.plateno.com/images/inn/18TROHr62E","skpUrl":"https://malls.bestwehotel.com/?sid=418002#/goodsDetail?productId=6000","point":"144积分"},{"resourceId":"20181010","title":"￥20","subTitle":null,"imageUrl":"https://imagemall.plateno.com/images/inn/18QVLnsmEc","skpUrl":"https://malls.bestwehotel.com/?sid=418002#/goodsDetail?productId=5772","point":"325积分"}]}}